[{"old":1,"new":[1],"status":"trivial_match","score":1},{"old":2,"new":[2],"status":"match","score":1},{"old":3,"new":[3],"status":"match","score":1},{"old":4,"new":[4],"status":"trivial_match","score":1},{"old":5,"new":[5],"status":"match","score":1},{"old":6,"new":[6],"status":"trivial_match","score":1},{"old":7,"new":[12],"status":"match","score":1},{"old":8,"new":[11],"status":"trivial_match","score":1},{"old":9,"new":[7],"status":"match","score":1},{"old":10,"new":[8],"status":"match","score":1},{"old":11,"new":[],"status":"unmatched","score":0},{"old":12,"new":[9],"status":"match","score":1},{"old":13,"new":[10],"status":"match","score":1},{"old":14,"new":[13],"status":"trivial_match","score":1},{"old":15,"new":[15],"status":"match","score":1},{"old":16,"new":[14],"status":"match","score":0.45833333333333326},{"old":17,"new":[16],"status":"match","score":1},{"old":18,"new":[17],"status":"trivial_match","score":1},{"old":19,"new":[18],"status":"match","score":1},{"old":20,"new":[19],"status":"match","score":1},{"old":21,"new":[20],"status":"trivial_match","score":1},{"old":22,"new":[21],"status":"match","score":1},{"old":23,"new":[22],"status":"match","score":1},{"old":24,"new":[26],"status":"match","score":0.3333333333333333},{"old":25,"new":[23],"status":"match","score":1},{"old":26,"new":[24],"status":"match","score":1},{"old":27,"new":[25],"status":"trivial_match","score":1},{"old":28,"new":[28],"status":"match","score":1},{"old":29,"new":[29],"status":"match","score":1},{"old":30,"new":[33],"status":"match","score":1},{"old":31,"new":[27],"status":"trivial_match","score":1},{"old":32,"new":[35],"status":"match","score":1},{"old":33,"new":[34],"status":"trivial_match","score":1},{"old":34,"new":[37],"status":"match","score":1},{"old":35,"new":[38,39],"status":"match_split","score":0.5636363636363636},{"old":36,"new":[],"status":"unmatched","score":0},{"old":37,"new":[],"status":"unmatched","score":0},{"old":38,"new":[41],"status":"match","score":0.3},{"old":39,"new":[36],"status":"trivial_match","score":1},{"old":40,"new":[43],"status":"match","score":1},{"old":41,"new":[44],"status":"match","score":1},{"old":42,"new":[45],"status":"match","score":1},{"old":43,"new":[46],"status":"match","score":1},{"old":44,"new":[],"status":"unmatched","score":0},{"old":45,"new":[40],"status":"trivial_match","score":1},{"old":46,"new":[],"status":"unmatched","score":0},{"old":47,"new":[50],"status":"match","score":0.3333333333333333},{"old":48,"new":[51],"status":"match","score":0.3333333333333333},{"old":49,"new":[52],"status":"match","score":0.3151515151515151},{"old":50,"new":[53],"status":"match","score":0.3151515151515151},{"old":51,"new":[42],"status":"trivial_match","score":1},{"old":52,"new":[],"status":"unmatched","score":0},{"old":53,"new":[48],"status":"trivial_match","score":1},{"old":54,"new":[56],"status":"trivial_match","score":1},{"old":55,"new":[60],"status":"trivial_match","score":1},{"old":56,"new":[57],"status":"match","score":1},{"old":57,"new":[58],"status":"match","score":0.41333333333333333},{"old":58,"new":[114],"status":"trivial_match","score":1},{"old":59,"new":[],"status":"unmatched","score":0},{"old":60,"new":[],"status":"unmatched","score":0},{"old":61,"new":[],"status":"unmatched","score":0},{"old":62,"new":[],"status":"unmatched","score":0},{"old":63,"new":[136],"status":"trivial_match","score":1},{"old":64,"new":[],"status":"unmatched","score":0},{"old":65,"new":[],"status":"unmatched","score":0},{"old":66,"new":[59],"status":"trivial_match","score":1},{"old":67,"new":[168],"status":"trivial_match","score":1},{"old":68,"new":[61],"status":"match","score":1},{"old":69,"new":[62],"status":"match","score":1},{"old":70,"new":[63],"status":"match","score":1},{"old":71,"new":[64],"status":"match","score":1},{"old":72,"new":[65],"status":"match","score":1},{"old":73,"new":[66],"status":"match","score":1},{"old":74,"new":[67],"status":"match","score":1},{"old":75,"new":[68],"status":"match","score":1},{"old":76,"new":[69],"status":"match","score":1},{"old":77,"new":[70],"status":"match","score":1},{"old":78,"new":[71],"status":"match","score":1},{"old":79,"new":[72],"status":"match","score":1},{"old":80,"new":[73],"status":"match","score":1},{"old":81,"new":[74],"status":"match","score":1},{"old":82,"new":[75],"status":"match","score":1},{"old":83,"new":[76],"status":"match","score":1},{"old":84,"new":[77],"status":"match","score":1},{"old":85,"new":[78],"status":"trivial_match","score":1},{"old":86,"new":[79],"status":"trivial_match","score":1},{"old":87,"new":[80],"status":"match","score":1},{"old":88,"new":[81],"status":"match","score":1},{"old":89,"new":[82],"status":"match","score":1},{"old":90,"new":[83],"status":"match","score":1},{"old":91,"new":[84],"status":"match","score":1},{"old":92,"new":[85],"status":"trivial_match","score":1},{"old":93,"new":[86],"status":"match","score":1},{"old":94,"new":[87],"status":"match","score":1},{"old":95,"new":[88],"status":"match","score":1},{"old":96,"new":[89],"status":"match","score":1},{"old":97,"new":[90],"status":"trivial_match","score":1},{"old":98,"new":[91],"status":"trivial_match","score":1},{"old":99,"new":[92],"status":"match","score":1},{"old":100,"new":[93],"status":"match","score":1},{"old":101,"new":[94],"status":"trivial_match","score":1},{"old":102,"new":[95],"status":"match","score":1},{"old":103,"new":[96],"status":"match","score":1},{"old":104,"new":[97],"status":"match","score":1},{"old":105,"new":[98],"status":"match","score":1},{"old":106,"new":[99],"status":"match","score":1},{"old":107,"new":[100],"status":"match","score":1},{"old":108,"new":[101],"status":"match","score":1},{"old":109,"new":[102],"status":"trivial_match","score":1},{"old":110,"new":[103],"status":"match","score":1},{"old":111,"new":[104],"status":"trivial_match","score":1},{"old":112,"new":[105],"status":"match","score":1},{"old":113,"new":[106],"status":"match","score":1},{"old":114,"new":[107],"status":"match","score":1},{"old":115,"new":[108],"status":"match","score":1},{"old":116,"new":[109],"status":"match","score":1},{"old":117,"new":[110],"status":"match","score":1},{"old":118,"new":[111],"status":"match","score":1},{"old":119,"new":[112],"status":"trivial_match","score":1},{"old":120,"new":[113],"status":"match","score":1},{"old":121,"new":[182],"status":"trivial_match","score":1},{"old":122,"new":[115],"status":"trivial_match","score":1},{"old":123,"new":[116],"status":"match","score":1},{"old":124,"new":[117],"status":"match","score":1},{"old":125,"new":[118],"status":"match","score":1},{"old":126,"new":[119],"status":"match","score":1},{"old":127,"new":[120],"status":"match","score":1},{"old":128,"new":[121],"status":"match","score":1},{"old":129,"new":[122],"status":"match","score":1},{"old":130,"new":[123],"status":"match","score":1},{"old":131,"new":[124],"status":"match","score":1},{"old":132,"new":[125],"status":"match","score":1},{"old":133,"new":[126],"status":"trivial_match","score":1},{"old":134,"new":[127],"status":"trivial_match","score":1},{"old":135,"new":[128],"status":"match","score":1},{"old":136,"new":[129],"status":"trivial_match","score":1},{"old":137,"new":[130],"status":"match","score":1},{"old":138,"new":[131],"status":"match","score":1},{"old":139,"new":[132],"status":"trivial_match","score":1},{"old":140,"new":[133],"status":"trivial_match","score":1},{"old":141,"new":[134],"status":"match","score":1},{"old":142,"new":[135],"status":"trivial_match","score":1},{"old":143,"new":[183],"status":"trivial_match","score":1},{"old":144,"new":[169],"status":"match","score":1},{"old":145,"new":[170],"status":"match","score":1},{"old":146,"new":[171],"status":"match","score":0.4221052631578947},{"old":147,"new":[138],"status":"match","score":1},{"old":148,"new":[139],"status":"match","score":1},{"old":149,"new":[],"status":"unmatched","score":0},{"old":150,"new":[140],"status":"match","score":1},{"old":151,"new":[146],"status":"match","score":1},{"old":152,"new":[],"status":"unmatched","score":0},{"old":153,"new":[148],"status":"trivial_match","score":1},{"old":154,"new":[141],"status":"match","score":1},{"old":155,"new":[174],"status":"match","score":0.39736842105263154},{"old":156,"new":[142],"status":"match","score":1},{"old":157,"new":[143],"status":"match","score":1},{"old":158,"new":[144],"status":"match","score":1},{"old":159,"new":[145],"status":"match","score":1},{"old":160,"new":[152],"status":"match","score":1},{"old":161,"new":[147],"status":"match","score":1},{"old":162,"new":[154],"status":"trivial_match","score":1},{"old":163,"new":[149],"status":"match","score":1},{"old":164,"new":[150],"status":"match","score":1},{"old":165,"new":[151],"status":"match","score":1},{"old":166,"new":[155],"status":"match","score":1},{"old":167,"new":[153],"status":"match","score":1},{"old":168,"new":[157],"status":"trivial_match","score":1},{"old":169,"new":[],"status":"unmatched","score":0},{"old":170,"new":[156],"status":"match","score":1},{"old":171,"new":[166],"status":"trivial_match","score":1},{"old":172,"new":[],"status":"unmatched","score":0},{"old":173,"new":[],"status":"unmatched","score":0},{"old":174,"new":[167],"status":"trivial_match","score":1},{"old":175,"new":[158],"status":"match","score":1},{"old":176,"new":[],"status":"unmatched","score":0},{"old":177,"new":[159],"status":"match","score":1},{"old":178,"new":[],"status":"unmatched","score":0},{"old":179,"new":[],"status":"unmatched","score":0},{"old":180,"new":[176],"status":"trivial_match","score":1},{"old":181,"new":[160],"status":"match","score":1},{"old":182,"new":[],"status":"unmatched","score":0},{"old":183,"new":[161],"status":"match","score":1},{"old":184,"new":[],"status":"unmatched","score":0},{"old":185,"new":[],"status":"unmatched","score":0},{"old":186,"new":[178],"status":"trivial_match","score":1},{"old":187,"new":[162],"status":"match","score":1},{"old":188,"new":[],"status":"unmatched","score":0},{"old":189,"new":[163],"status":"match","score":1},{"old":190,"new":[],"status":"unmatched","score":0},{"old":191,"new":[],"status":"unmatched","score":0},{"old":192,"new":[179],"status":"trivial_match","score":1},{"old":193,"new":[164],"status":"match","score":1},{"old":194,"new":[],"status":"unmatched","score":0},{"old":195,"new":[181],"status":"trivial_match","score":1},{"old":196,"new":[184],"status":"trivial_match","score":1},{"old":197,"new":[165],"status":"match","score":1}]